TradeMaster/TradeSync.py
TradeMaster/__init__.py
TradeMaster/base_validation/__init__.py
TradeMaster/base_validation/_orderValidation.py
TradeMaster/base_validation/checksum.py
TradeMaster/base_validation/file_read.py
TradeMaster/base_validation/timestamp.py
TradeMaster/network/__init__.py
TradeMaster/network/api_client.py
TradeMaster/network/device_identifier.py
config/__init__.py
config/config.py
config/settings.py
utility/__init__.py
utility/library.py
rmoney_tradion_uat-1.1.3.dist-info/METADATA
rmoney_tradion_uat-1.1.3.dist-info/WHEEL
rmoney_tradion_uat-1.1.3.dist-info/top_level.txt
rmoney_tradion_uat-1.1.3.dist-info/RECORD
