Metadata-Version: 2.1
Name: rmoney-tradion-uat
Version: 1.1.3
Summary: Python SDK for integrating with Aliceblue trading platform.
Home-page: https://weblive.rmoneyindia.net/
Author: Codifi
Author-email: periyasamy@codifi.in
License: MIT
Project-URL: Documentation, https://weblive.rmoneyindia.net/apidocs/
Platform: UNKNOWN
Classifier: Programming Language :: Python :: 3.8
Classifier: License :: OSI Approved :: MIT License
Classifier: Operating System :: OS Independent
Classifier: Natural Language :: English
Classifier: Intended Audience :: Developers
Requires-Python: >=3.7
Requires-Dist: requests
Requires-Dist: pandas
Requires-Dist: websocket-client
Requires-Dist: rel
